{"PART": {"name": "mk2FuselageShortLiquid", "module": "Part", "author": "Porkjet", "rescaleFactor": 1, "node_stack_top": [0.0, 0.9375, 0.0, 0.0, 1.0, 0.0], "node_stack_bottom": [0.0, -0.9375, 0.0, 0.0, -1.0, 0.0], "node_attach": [1.25, 0.0, 0.0, 1.0, 0.0, 0.0, 1], "mirrorRefAxis": [0, 0, -1.0], "TechRequired": "supersonicFlight", "entryCost": 18500, "cost": 750, "category": "Propulsion", "subcategory": 0, "title": "#autoLOC_500571", "manufacturer": "#autoLOC_501624", "description": "#autoLOC_500572", "attachRules": [1, 1, 1, 1, 0], "mass": 0.29, "dragModelType": "default", "maximum_drag": 0.2, "minimum_drag": 0.3, "angularDrag": 1, "crashTolerance": 50, "breakingForce": 50, "breakingTorque": 50, "maxTemp": 2500, "emissiveConstant": 0.8, "fuelCrossFeed": true, "bulkheadProfiles": ["mk2", "srf"], "tags": "#autoLOC_500573", "MODEL": {"model": "Squad/Parts/FuelTank/mk2FuselageShort/FuselageShortLiquid"}, "MODULE": [{"name": "ModuleLiftingSurface", "useInternalDragModel": false, "deflectionLiftCoeff": 0.35, "dragAtMaxAoA": 0.15, "dragAtMinAoA": 0.1}, {"name": "ModuleCargoPart", "stackableQuantity": 1, "packedVolume": -1.0}], "RESOURCE": {"name": "LiquidFuel", "amount": 400, "maxAmount": 400}}}